TERRA_GA/IMG_Classification_GA.py
TERRA_GA/__init__.py
UII_GA_IMG_Classification-0.0.18.dist-info/LICENSE.txt
UII_GA_IMG_Classification-0.0.18.dist-info/METADATA
UII_GA_IMG_Classification-0.0.18.dist-info/WHEEL
UII_GA_IMG_Classification-0.0.18.dist-info/top_level.txt
UII_GA_IMG_Classification-0.0.18.dist-info/RECORD
